notetool/__init__.py
notetool/convert/__init__.py
notetool/convert/curl2py.py
notetool/crawler/__init__.py
notetool/crawler/ba.py
notetool/crawler/core.py
notetool/crawler/movies.py
notetool/database/__init__.py
notetool/database/core.py
notetool/download/__init__.py
notetool/download/core.py
notetool/download/m3u8.py
notetool/download/story.py
notetool/everything/__init__.py
notetool/everything/d2lzh.py
notetool/load/__init__.py
notetool/load/core.py
notetool/log/__init__.py
notetool/log/log.py
notetool/log/log_widget.py
notetool/math/__init__.py
notetool/math/prime.py
notetool/path/__init__.py
notetool/path/core.py
notetool/secret/__init__.py
notetool/secret/secret.py
notetool/time/__init__.py
notetool/time/core.py
notetool/tool/__init__.py
notetool/tool/build.py
notetool/tool/compress.py
notetool/tool/log.py
notetool/tool/path.py
notetool/tool/pyrss.py
notetool/tool/time.py
notetool/tool/tool.py
notetool/utils/__init__.py
notetool/utils/struct.py
notetool-0.6.21.dist-info/LICENSE
notetool-0.6.21.dist-info/METADATA
notetool-0.6.21.dist-info/WHEEL
notetool-0.6.21.dist-info/top_level.txt
notetool-0.6.21.dist-info/RECORD
