Metadata-Version: 2.1
Name: notetool
Version: 0.6.21
Summary: notetool
Home-page: https://github.com/1007530194
Author: niuliangtao
Author-email: 1007530194@qq.com
License: UNKNOWN
Platform: UNKNOWN
License-File: LICENSE
Requires-Dist: cryptography
Requires-Dist: notebuild
